tttarena/__init__.py
tttarena/bots/base_bot.py
tttarena/bots/simple_bot.py
tttarena/engine/core/engine.py
tttarena/engine/core/exceptions.py
tttarena/engine/core/geometry.py
tttarena/engine/sculptor/generators.py
tttarena/engine/sculptor/metrics.py
tttarena/simulator/logger.py
tttarena/simulator/runner.py
tttarena/simulator/visualizer.py
tttarena/simulator/visualizers/base_visualizer.py
tttarena/simulator/visualizers/cli_visualizer.py
tttarena/simulator/visualizers/pygame_visualizer.py
tttarena/verifier.py
tttarena-0.1.2.dist-info/LICENSE
tttarena-0.1.2.dist-info/METADATA
tttarena-0.1.2.dist-info/WHEEL
tttarena-0.1.2.dist-info/RECORD
