Metadata-Version: 2.3
Name: tttarena
Version: 0.1.2
Summary: Deterministic, turn-based Tetris engine with 'Nightmare' mechanics (target curve, petrification, entropy budget)
License: MIT
Author: naereni
Requires-Python: >=3.11
Classifier: License :: OSI Approved :: MIT License
Classifier: Programming Language :: Python :: 3
Classifier: Programming Language :: Python :: 3.11
Classifier: Programming Language :: Python :: 3.12
Classifier: Programming Language :: Python :: 3.13
Requires-Dist: numba (>=0.60.0,<0.63.0)
Requires-Dist: numpy (>=2.0.0,<3.0.0)
Requires-Dist: tqdm (>=4.67.0,<5.0.0)
Project-URL: Bug Tracker, https://github.com/naereni/tttarena/issues
Project-URL: Homepage, https://github.com/naereni/tttarena
